windrak/__init__.py
windrak/cli.py
windrak/create_pr.py
windrak/create_readme.py
windrak/utils.py
windrak-0.1.7.dist-info/LICENSE
windrak-0.1.7.dist-info/METADATA
windrak-0.1.7.dist-info/WHEEL
windrak-0.1.7.dist-info/entry_points.txt
windrak-0.1.7.dist-info/top_level.txt
windrak-0.1.7.dist-info/RECORD
